pyfortysevenreel/__init__.py
pyfortysevenreel/greetings.py
pyfortysevenreel-0.0.1.dist-info/METADATA
pyfortysevenreel-0.0.1.dist-info/WHEEL
pyfortysevenreel-0.0.1.dist-info/top_level.txt
pyfortysevenreel-0.0.1.dist-info/RECORD
