Metadata-Version: 2.4
Name: pyfortysevenreel
Version: 0.0.1
Summary: A package to greet
Home-page: https://github.com/fortysev-en/pyfortysevenreel
Author: Pushkar Jadhav
Author-email: pushkar.jadhao@gmail.com
Classifier: Programming Language :: Python :: 3
Classifier: Operating System :: OS Independent
Requires-Python: >=3.7
